abcdefgji_ti/__init__.py
abcdefgji_ti/api_client.py
abcdefgji_ti/api_response.py
abcdefgji_ti/configuration.py
abcdefgji_ti/exceptions.py
abcdefgji_ti/py.typed
abcdefgji_ti/rest.py
abcdefgji_ti/api/__init__.py
abcdefgji_ti/api/abuse_reports_api.py
abcdefgji_ti/api/activities_api.py
abcdefgji_ti/api/captions_api.py
abcdefgji_ti/api/channel_banners_api.py
abcdefgji_ti/api/channel_sections_api.py
abcdefgji_ti/api/channels_api.py
abcdefgji_ti/api/comment_threads_api.py
abcdefgji_ti/api/comments_api.py
abcdefgji_ti/api/i18n_languages_api.py
abcdefgji_ti/api/i18n_regions_api.py
abcdefgji_ti/api/live_broadcasts_api.py
abcdefgji_ti/api/live_chat_bans_api.py
abcdefgji_ti/api/live_chat_messages_api.py
abcdefgji_ti/api/live_chat_moderators_api.py
abcdefgji_ti/api/live_streams_api.py
abcdefgji_ti/api/members_api.py
abcdefgji_ti/api/memberships_levels_api.py
abcdefgji_ti/api/playlist_images_api.py
abcdefgji_ti/api/playlist_items_api.py
abcdefgji_ti/api/playlists_api.py
abcdefgji_ti/api/search_api.py
abcdefgji_ti/api/subscriptions_api.py
abcdefgji_ti/api/super_chat_events_api.py
abcdefgji_ti/api/tests_api.py
abcdefgji_ti/api/third_party_links_api.py
abcdefgji_ti/api/thumbnails_api.py
abcdefgji_ti/api/video_abuse_report_reasons_api.py
abcdefgji_ti/api/video_categories_api.py
abcdefgji_ti/api/video_trainability_api.py
abcdefgji_ti/api/videos_api.py
abcdefgji_ti/api/watermarks_api.py
abcdefgji_ti/api/youtube_api.py
abcdefgji_ti/models/__init__.py
abcdefgji_ti/models/abuse_report.py
abcdefgji_ti/models/abuse_type.py
abcdefgji_ti/models/access_policy.py
abcdefgji_ti/models/activity.py
abcdefgji_ti/models/activity_content_details.py
abcdefgji_ti/models/activity_content_details_bulletin.py
abcdefgji_ti/models/activity_content_details_channel_item.py
abcdefgji_ti/models/activity_content_details_comment.py
abcdefgji_ti/models/activity_content_details_favorite.py
abcdefgji_ti/models/activity_content_details_like.py
abcdefgji_ti/models/activity_content_details_playlist_item.py
abcdefgji_ti-0.0.1.dist-info/METADATA
abcdefgji_ti-0.0.1.dist-info/WHEEL
abcdefgji_ti-0.0.1.dist-info/top_level.txt
abcdefgji_ti-0.0.1.dist-info/RECORD
